nonebot_plugin_mqtt/__init__.py
nonebot_plugin_mqtt/config.py
nonebot_plugin_mqtt/mqtt.py
nonebot_plugin_mqtt-0.1.2.dist-info/LICENSE
nonebot_plugin_mqtt-0.1.2.dist-info/METADATA
nonebot_plugin_mqtt-0.1.2.dist-info/WHEEL
nonebot_plugin_mqtt-0.1.2.dist-info/top_level.txt
nonebot_plugin_mqtt-0.1.2.dist-info/RECORD
